<annotation>
	<folder></folder>
	<filename>WIN_20230301_18_59_17_Pro_jpg.rf.d4aeef4e353ef5dcd41bf968b19cada6.jpg</filename>
	<path>WIN_20230301_18_59_17_Pro_jpg.rf.d4aeef4e353ef5dcd41bf968b19cada6.jpg</path>
	<source>
		<database>roboflow.ai</database>
	</source>
	<size>
		<width>224</width>
		<height>224</height>
		<depth>3</depth>
	</size>
	<segmented>0</segmented>
	<object>
		<name>Cut</name>
		<pose>Unspecified</pose>
		<truncated>0</truncated>
		<difficult>0</difficult>
		<occluded>0</occluded>
		<bndbox>
			<xmin>2</xmin>
			<xmax>225</xmax>
			<ymin>8</ymin>
			<ymax>217</ymax>
		</bndbox>
	</object>
</annotation>
